pysubconverter.libs/libstdc++-0530927c.so.6.0.32
pysubconverter.libs/libgcc_s-1257a076.so.1
pysubconverter/_core.pyi
pysubconverter/_core.cpython-310-i386-linux-gnu.so
pysubconverter/_version.py
pysubconverter/py.typed
pysubconverter/_version.pyi
pysubconverter/__init__.py
pysubconverter/config/pref.example.ini
pysubconverter/config/pref.example.toml
pysubconverter/config/pref.example.yml
pysubconverter/config/gistconf.ini
pysubconverter/config/generate.ini
pysubconverter/config/config/example_external_config.yml
pysubconverter/config/config/ACL4SSR_Online_Full_Netflix.ini
pysubconverter/config/config/ACL4SSR_Online_Mini_AdblockPlus.ini
pysubconverter/config/config/ACL4SSR_Mini.ini
pysubconverter/config/config/ACL4SSR_Online_Mini.ini
pysubconverter/config/config/ACL4SSR_Mini_MultiMode.ini
pysubconverter/config/config/example_external_config.ini
pysubconverter/config/config/ACL4SSR_Online_Full_Google.ini
pysubconverter/config/config/ACL4SSR_Online_Mini_MultiCountry.ini
pysubconverter/config/config/ACL4SSR_Online_Full_NoAuto.ini
pysubconverter/config/config/ACL4SSR_Online_MultiCountry.ini
pysubconverter/config/config/ACL4SSR_Online_NoAuto.ini
pysubconverter/config/config/ACL4SSR_Mini_Fallback.ini
pysubconverter/config/config/ACL4SSR_WithGFW.ini
pysubconverter/config/config/ACL4SSR_NoAuto_NoApple_NoMicrosoft.ini
pysubconverter/config/config/ACL4SSR_WithChinaIp.ini
pysubconverter/config/config/ACL4SSR_Online_Mini_NoAuto.ini
pysubconverter/config/config/ACL4SSR_Online_Full_AdblockPlus.ini
pysubconverter/config/config/ACL4SSR_AdblockPlus.ini
pysubconverter/config/config/ACL4SSR_Online_Mini_Fallback.ini
pysubconverter/config/config/ACL4SSR_Online_AdblockPlus.ini
pysubconverter/config/config/ACL4SSR_NoMicrosoft.ini
pysubconverter/config/config/ACL4SSR_NoApple.ini
pysubconverter/config/config/example_external_config.toml
pysubconverter/config/config/ACL4SSR_Online_Full.ini
pysubconverter/config/config/ACL4SSR_Online_NoReject.ini
pysubconverter-0.2.0.dist-info/WHEEL
pysubconverter-0.2.0.dist-info/RECORD
pysubconverter-0.2.0.dist-info/METADATA
pysubconverter-0.2.0.dist-info/licenses/LICENSE
