Metadata-Version: 2.1
Name: pysubconverter
Version: 0.2.0
Summary: A wrapper from subconverter
Author-Email: "l.feng" <msclock@126.com>
License: MIT
Classifier: Intended Audience :: Science/Research
Classifier: Intended Audience :: Developers
Classifier: License :: OSI Approved :: MIT License
Classifier: Operating System :: OS Independent
Classifier: Programming Language :: Python
Classifier: Programming Language :: Python :: 3
Classifier: Programming Language :: Python :: 3 :: Only
Classifier: Programming Language :: Python :: 3.8
Classifier: Programming Language :: Python :: 3.9
Classifier: Programming Language :: Python :: 3.10
Classifier: Programming Language :: Python :: 3.11
Classifier: Programming Language :: Python :: 3.12
Classifier: Topic :: Scientific/Engineering
Classifier: Typing :: Typed
Project-URL: Homepage, https://github.com/msclock/pysubconverter
Project-URL: Bug Tracker, https://github.com/msclock/pysubconverter/issues
Project-URL: Discussions, https://github.com/msclock/pysubconverter/discussions
Project-URL: Changelog, https://github.com/msclock/pysubconverter/releases
Requires-Python: >=3.8
Requires-Dist: typing-extensions>=3.10.0; python_version < "3.9"
Requires-Dist: importlib_metadata>=1.4
Requires-Dist: PyYAML>=6.0.2
Requires-Dist: appdirs==1.4.4
Requires-Dist: filelock
Provides-Extra: test
Requires-Dist: pytest>=6; extra == "test"
Requires-Dist: pytest-cov>=3; extra == "test"
Provides-Extra: dev
Requires-Dist: pytest>=6; extra == "dev"
Requires-Dist: pytest-cov>=3; extra == "dev"
Provides-Extra: docs
Requires-Dist: mkdocs>=1.6.0; extra == "docs"
Requires-Dist: mkdocs-git-revision-date-localized-plugin>=1.2.6; extra == "docs"
Requires-Dist: mkdocs-material>=9.5.29; extra == "docs"
Requires-Dist: mkdocs-minify-plugin>=0.8.0; extra == "docs"
Requires-Dist: mkdocs-same-dir>=0.1.3; extra == "docs"
